html_tag_action_mapper/__init__.py
html_tag_action_mapper/action_mapper.py
html_tag_action_mapper/static/tag2action.txt
html_tag_action_mapper-0.1.5.dist-info/METADATA
html_tag_action_mapper-0.1.5.dist-info/WHEEL
html_tag_action_mapper-0.1.5.dist-info/top_level.txt
html_tag_action_mapper-0.1.5.dist-info/RECORD
