Metadata-Version: 2.1
Name: html-tag-action-mapper
Version: 0.1.5
Summary: Demo library
Home-page: UNKNOWN
License: UNKNOWN
Platform: UNKNOWN
Classifier: Intended Audience :: Developers
Classifier: Programming Language :: Python
Classifier: Operating System :: OS Independent
